README.txt
setup.py
repoze/__init__.py
repoze.slicer.egg-info/PKG-INFO
repoze.slicer.egg-info/SOURCES.txt
repoze.slicer.egg-info/dependency_links.txt
repoze.slicer.egg-info/entry_points.txt
repoze.slicer.egg-info/namespace_packages.txt
repoze.slicer.egg-info/requires.txt
repoze.slicer.egg-info/top_level.txt
repoze.slicer.egg-info/zip-safe
repoze/slicer/__init__.py
repoze/slicer/tests.py