Metadata-Version: 1.0
Name: repoze.slicer
Version: 1.0a2
Summary: WSGI middleware to filter HTML responses
Home-page: http://www.repoze.org
Author: Wichert Akkerman
Author-email: repoze-dev@lists.repoze.org
License: BSD
Keywords: wsgi html transformation
Platform: UNKNOWN
Classifier: Intended Audience :: Developers
Classifier: Programming Language :: Python
Classifier: Topic :: Internet :: WWW/HTTP
Classifier: Topic :: Internet :: WWW/HTTP :: Dynamic Content
Classifier: Topic :: Internet :: WWW/HTTP :: WSGI
